Workbook

Sheet Raw Data
A1: Age | B1: Attrition | C1: BusinessTravel | D1: DailyRate | E1: Department | F1: DistanceFromHome | G1: Education | H1: EducationField | I1: EmployeeCount | J1: EmployeeNumber | K1: EnvironmentSatisfaction | L1: Gender | M1: HourlyRate | N1: JobInvolvement | O1: JobLevel | P1: JobRole | Q1: JobSatisfaction | R1: MaritalStatus | S1: MonthlyIncome | T1: MonthlyRate | U1: NumCompaniesWorked | V1: Over18 | W1: OverTime | X1: PercentSalaryHike | Y1: PerformanceRating | Z1: RelationshipSatisfaction | AA1: StandardHours | AB1: StockOptionLevel | AC1: TotalWorkingYears | AD1: TrainingTimesLastYear | AE1: WorkLifeBalance | AF1: YearsAtCompany | AG1: YearsInCurrentRole | AH1: YearsSinceLastPromotion | AI1: YearsWithCurrManager | AJ1: Total Employees | AK1: Total Who Left | AL1: Attrition Rate
A2: 41 | B2: Yes | C2: Travel_Rarely | D2: 1102 | E2: Sales | F2: 1 | G2: 2 | H2: Life Sciences | I2: 1 | J2: 1 | K2: 2 | L2: Female | M2: 94 | N2: 3 | O2: 2 | P2: Sales Executive | Q2: 4 | R2: Single | S2: 5993 | T2: 19479 | U2: 8 | V2: Y | W2: Yes | X2: 11 | Y2: 3 | Z2: 1 | AA2: 80 | AB2: 0 | AC2: 8 | AD2: 0 | AE2: 1 | AF2: 6 | AG2: 4 | AH2: 0 | AI2: 5 | AJ2: =COUNTA(A2:A1471) -> 1470 | AK2: =COUNTIF(B2:B1471, "Yes") -> 237 | AL2: =COUNTIF(B2:B1471, "Yes")/COUNTA(A2:A1471) -> 0.16122449
A3: 49 | B3: No | C3: Travel_Frequently | D3: 279 | E3: Research & Development | F3: 8 | G3: 1 | H3: Life Sciences | I3: 1 | J3: 2 | K3: 3 | L3: Male | M3: 61 | N3: 2 | O3: 2 | P3: Research Scientist | Q3: 2 | R3: Married | S3: 5130 | T3: 24907 | U3: 1 | V3: Y | W3: No | X3: 23 | Y3: 4 | Z3: 4 | AA3: 80 | AB3: 1 | AC3: 10 | AD3: 3 | AE3: 3 | AF3: 10 | AG3: 7 | AH3: 1 | AI3: 7 | AJ3: =COUNTA(A3:A1472) -> 1469 | AK3: =COUNTIF(B3:B1472, "Yes") -> 236 | AL3: =COUNTIF(B3:B1472, "Yes")/COUNTA(A3:A1472) -> 0.16065351
A4: 37 | B4: Yes | C4: Travel_Rarely | D4: 1373 | E4: Research & Development | F4: 2 | G4: 2 | H4: Other | I4: 1 | J4: 4 | K4: 4 | L4: Male | M4: 92 | N4: 2 | O4: 1 | P4: Laboratory Technician | Q4: 3 | R4: Single | S4: 2090 | T4: 2396 | U4: 6 | V4: Y | W4: Yes | X4: 15 | Y4: 3 | Z4: 2 | AA4: 80 | AB4: 0 | AC4: 7 | AD4: 3 | AE4: 3 | AF4: 0 | AG4: 0 | AH4: 0 | AI4: 0 | AJ4: =COUNTA(A4:A1473) -> 1468 | AK4: =COUNTIF(B4:B1473, "Yes") -> 236 | AL4: =COUNTIF(B4:B1473, "Yes")/COUNTA(A4:A1473) -> 0.16076294
A5: 33 | B5: No | C5: Travel_Frequently | D5: 1392 | E5: Research & Development | F5: 3 | G5: 4 | H5: Life Sciences | I5: 1 | J5: 5 | K5: 4 | L5: Female | M5: 56 | N5: 3 | O5: 1 | P5: Research Scientist | Q5: 3 | R5: Married | S5: 2909 | T5: 23159 | U5: 1 | V5: Y | W5: Yes | X5: 11 | Y5: 3 | Z5: 3 | AA5: 80 | AB5: 0 | AC5: 8 | AD5: 3 | AE5: 3 | AF5: 8 | AG5: 7 | AH5: 3 | AI5: 0 | AJ5: =COUNTA(A5:A1474) -> 1467 | AK5: =COUNTIF(B5:B1474, "Yes") -> 235 | AL5: =COUNTIF(B5:B1474, "Yes")/COUNTA(A5:A1474) -> 0.16019087
A6: 27 | B6: No | C6: Travel_Rarely | D6: 591 | E6: Research & Development | F6: 2 | G6: 1 | H6: Medical | I6: 1 | J6: 7 | K6: 1 | L6: Male | M6: 40 | N6: 3 | O6: 1 | P6: Laboratory Technician | Q6: 2 | R6: Married | S6: 3468 | T6: 16632 | U6: 9 | V6: Y | W6: No | X6: 12 | Y6: 3 | Z6: 4 | AA6: 80 | AB6: 1 | AC6: 6 | AD6: 3 | AE6: 3 | AF6: 2 | AG6: 2 | AH6: 2 | AI6: 2 | AJ6: =COUNTA(A6:A1475) -> 1466 | AK6: =COUNTIF(B6:B1475, "Yes") -> 235 | AL6: =COUNTIF(B6:B1475, "Yes")/COUNTA(A6:A1475) -> 0.16030014
A7: 32 | B7: No | C7: Travel_Frequently | D7: 1005 | E7: Research & Development | F7: 2 | G7: 2 | H7: Life Sciences | I7: 1 | J7: 8 | K7: 4 | L7: Male | M7: 79 | N7: 3 | O7: 1 | P7: Laboratory Technician | Q7: 4 | R7: Single | S7: 3068 | T7: 11864 | U7: 0 | V7: Y | W7: No | X7: 13 | Y7: 3 | Z7: 3 | AA7: 80 | AB7: 0 | AC7: 8 | AD7: 2 | AE7: 2 | AF7: 7 | AG7: 7 | AH7: 3 | AI7: 6 | AJ7: =COUNTA(A7:A1476) -> 1465 | AK7: =COUNTIF(B7:B1476, "Yes") -> 235 | AL7: =COUNTIF(B7:B1476, "Yes")/COUNTA(A7:A1476) -> 0.16040956
A8: 59 | B8: No | C8: Travel_Rarely | D8: 1324 | E8: Research & Development | F8: 3 | G8: 3 | H8: Medical | I8: 1 | J8: 10 | K8: 3 | L8: Female | M8: 81 | N8: 4 | O8: 1 | P8: Laboratory Technician | Q8: 1 | R8: Married | S8: 2670 | T8: 9964 | U8: 4 | V8: Y | W8: Yes | X8: 20 | Y8: 4 | Z8: 1 | AA8: 80 | AB8: 3 | AC8: 12 | AD8: 3 | AE8: 2 | AF8: 1 | AG8: 0 | AH8: 0 | AI8: 0 | AJ8: =COUNTA(A8:A1477) -> 1464 | AK8: =COUNTIF(B8:B1477, "Yes") -> 235 | AL8: =COUNTIF(B8:B1477, "Yes")/COUNTA(A8:A1477) -> 0.16051913
A9: 30 | B9: No | C9: Travel_Rarely | D9: 1358 | E9: Research & Development | F9: 24 | G9: 1 | H9: Life Sciences | I9: 1 | J9: 11 | K9: 4 | L9: Male | M9: 67 | N9: 3 | O9: 1 | P9: Laboratory Technician | Q9: 3 | R9: Divorced | S9: 2693 | T9: 13335 | U9: 1 | V9: Y | W9: No | X9: 22 | Y9: 4 | Z9: 2 | AA9: 80 | AB9: 1 | AC9: 1 | AD9: 2 | AE9: 3 | AF9: 1 | AG9: 0 | AH9: 0 | AI9: 0 | AJ9: =COUNTA(A9:A1478) -> 1463 | AK9: =COUNTIF(B9:B1478, "Yes") -> 235 | AL9: =COUNTIF(B9:B1478, "Yes")/COUNTA(A9:A1478) -> 0.16062884
A10: 38 | B10: No | C10: Travel_Frequently | D10: 216 | E10: Research & Development | F10: 23 | G10: 3 | H10: Life Sciences | I10: 1 | J10: 12 | K10: 4 | L10: Male | M10: 44 | N10: 2 | O10: 3 | P10: Manufacturing Director | Q10: 3 | R10: Single | S10: 9526 | T10: 8787 | U10: 0 | V10: Y | W10: No | X10: 21 | Y10: 4 | Z10: 2 | AA10: 80 | AB10: 0 | AC10: 10 | AD10: 2 | AE10: 3 | AF10: 9 | AG10: 7 | AH10: 1 | AI10: 8 | AJ10: =COUNTA(A10:A1479) -> 1462 | AK10: =COUNTIF(B10:B1479, "Yes") -> 235 | AL10: =COUNTIF(B10:B1479, "Yes")/COUNTA(A10:A1479) -> 0.16073871
A11: 36 | B11: No | C11: Travel_Rarely | D11: 1299 | E11: Research & Development | F11: 27 | G11: 3 | H11: Medical | I11: 1 | J11: 13 | K11: 3 | L11: Male | M11: 94 | N11: 3 | O11: 2 | P11: Healthcare Representative | Q11: 3 | R11: Married | S11: 5237 | T11: 16577 | U11: 6 | V11: Y | W11: No | X11: 13 | Y11: 3 | Z11: 2 | AA11: 80 | AB11: 2 | AC11: 17 | AD11: 3 | AE11: 2 | AF11: 7 | AG11: 7 | AH11: 7 | AI11: 7 | AJ11: =COUNTA(A11:A1480) -> 1461 | AK11: =COUNTIF(B11:B1480, "Yes") -> 235 | AL11: =COUNTIF(B11:B1480, "Yes")/COUNTA(A11:A1480) -> 0.16084873
A12: 35 | B12: No | C12: Travel_Rarely | D12: 809 | E12: Research & Development | F12: 16 | G12: 3 | H12: Medical | I12: 1 | J12: 14 | K12: 1 | L12: Male | M12: 84 | N12: 4 | O12: 1 | P12: Laboratory Technician | Q12: 2 | R12: Married | S12: 2426 | T12: 16479 | U12: 0 | V12: Y | W12: No | X12: 13 | Y12: 3 | Z12: 3 | AA12: 80 | AB12: 1 | AC12: 6 | AD12: 5 | AE12: 3 | AF12: 5 | AG12: 4 | AH12: 0 | AI12: 3 | AJ12: =COUNTA(A12:A1481) -> 1460 | AK12: =COUNTIF(B12:B1481, "Yes") -> 235 | AL12: =COUNTIF(B12:B1481, "Yes")/COUNTA(A12:A1481) -> 0.1609589
A13: 29 | B13: No | C13: Travel_Rarely | D13: 153 | E13: Research & Development | F13: 15 | G13: 2 | H13: Life Sciences | I13: 1 | J13: 15 | K13: 4 | L13: Female | M13: 49 | N13: 2 | O13: 2 | P13: Laboratory Technician | Q13: 3 | R13: Single | S13: 4193 | T13: 12682 | U13: 0 | V13: Y | W13: Yes | X13: 12 | Y13: 3 | Z13: 4 | AA13: 80 | AB13: 0 | AC13: 10 | AD13: 3 | AE13: 3 | AF13: 9 | AG13: 5 | AH13: 0 | AI13: 8 | AJ13: =COUNTA(A13:A1482) -> 1459 | AK13: =COUNTIF(B13:B1482, "Yes") -> 235 | AL13: =COUNTIF(B13:B1482, "Yes")/COUNTA(A13:A1482) -> 0.16106923
... A1471: 34 | B1471: No | C1471: Travel_Rarely | D1471: 628 | E1471: Research & Development | F1471: 8 | G1471: 3 | H1471: Medical | I1471: 1 | J1471: 2068 | K1471: 2 | L1471: Male | M1471: 82 | N1471: 4 | O1471: 2 | P1471: Laboratory Technician | Q1471: 3 | R1471: Married | S1471: 4404 | T1471: 10228 | U1471: 2 | V1471: Y | W1471: No | X1471: 12 | Y1471: 3 | Z1471: 1 | AA1471: 80 | AB1471: 0 | AC1471: 6 | AD1471: 3 | AE1471: 4 | AF1471: 4 | AG1471: 3 | AH1471: 1 | AI1471: 2 | AJ1471: =COUNTA(A1471:A2940) -> 1 | AK1471: =COUNTIF(B1471:B2940, "Yes") -> 0 | AL1471: =COUNTIF(B1471:B2940, "Yes")/COUNTA(A1471:A2940) -> 0

Sheet Analysis
A1: Department | B1: Total Employees | C1: Employees Left | D1: Attrition Rate | F1: Job Role | G1: Total Employees | H1: Empoyees Left | I1: Attrition Rate
A2: Human Resources | B2: =COUNTIF('Raw Data'!E:E, A2) -> 63 | C2: =COUNTIFS('Raw Data'!E:E, A2, 'Raw Data'!B:B, "Yes") -> 12 | D2: =COUNTIFS('Raw Data'!E:E, A2, 'Raw Data'!B:B, "Yes")/COUNTIF('Raw Data'!E:E, A2) -> 0.19047619 | F2: Sales Representative | G2: =COUNTIF('Raw Data'!P:P, F2) -> 83 | H2: =COUNTIFS('Raw Data'!P:P, F2, 'Raw Data'!B:B, "Yes") -> 33 | I2: =COUNTIFS('Raw Data'!P:P, F2, 'Raw Data'!B:B, "Yes")/COUNTIF('Raw Data'!P:P, F2) -> 0.39759036
A3: Research & Development | B3: =COUNTIF('Raw Data'!E:E, A3) -> 961 | C3: =COUNTIFS('Raw Data'!E:E, A3, 'Raw Data'!B:B, "Yes") -> 133 | D3: =COUNTIFS('Raw Data'!E:E, A3, 'Raw Data'!B:B, "Yes")/COUNTIF('Raw Data'!E:E, A3) -> 0.1383975 | F3: Laboratory Technician | G3: =COUNTIF('Raw Data'!P:P, F3) -> 259 | H3: =COUNTIFS('Raw Data'!P:P, F3, 'Raw Data'!B:B, "Yes") -> 62 | I3: =COUNTIFS('Raw Data'!P:P, F3, 'Raw Data'!B:B, "Yes")/COUNTIF('Raw Data'!P:P, F3) -> 0.23938224
A4: Sales | B4: =COUNTIF('Raw Data'!E:E, A4) -> 446 | C4: =COUNTIFS('Raw Data'!E:E, A4, 'Raw Data'!B:B, "Yes") -> 92 | D4: =COUNTIFS('Raw Data'!E:E, A4, 'Raw Data'!B:B, "Yes")/COUNTIF('Raw Data'!E:E, A4) -> 0.20627803 | F4: Human Resources | G4: =COUNTIF('Raw Data'!P:P, F4) -> 52 | H4: =COUNTIFS('Raw Data'!P:P, F4, 'Raw Data'!B:B, "Yes") -> 12 | I4: =COUNTIFS('Raw Data'!P:P, F4, 'Raw Data'!B:B, "Yes")/COUNTIF('Raw Data'!P:P, F4) -> 0.23076923
F5: Sales Executive | G5: =COUNTIF('Raw Data'!P:P, F5) -> 326 | H5: =COUNTIFS('Raw Data'!P:P, F5, 'Raw Data'!B:B, "Yes") -> 57 | I5: =COUNTIFS('Raw Data'!P:P, F5, 'Raw Data'!B:B, "Yes")/COUNTIF('Raw Data'!P:P, F5) -> 0.17484663
F6: Research Scientist | G6: =COUNTIF('Raw Data'!P:P, F6) -> 292 | H6: =COUNTIFS('Raw Data'!P:P, F6, 'Raw Data'!B:B, "Yes") -> 47 | I6: =COUNTIFS('Raw Data'!P:P, F6, 'Raw Data'!B:B, "Yes")/COUNTIF('Raw Data'!P:P, F6) -> 0.1609589
A7: Attrition Status | B7: Avg Monthly Income | F7: Manufacturing Director | G7: =COUNTIF('Raw Data'!P:P, F7) -> 145 | H7: =COUNTIFS('Raw Data'!P:P, F7, 'Raw Data'!B:B, "Yes") -> 10 | I7: =COUNTIFS('Raw Data'!P:P, F7, 'Raw Data'!B:B, "Yes")/COUNTIF('Raw Data'!P:P, F7) -> 0.068965517
A8: Yes | B8: =ROUND(AVERAGEIF('Raw Data'!B:B, A8, 'Raw Data'!S:S), 2) -> 4787.09 | F8: Healthcare Representative | G8: =COUNTIF('Raw Data'!P:P, F8) -> 131 | H8: =COUNTIFS('Raw Data'!P:P, F8, 'Raw Data'!B:B, "Yes") -> 9 | I8: =COUNTIFS('Raw Data'!P:P, F8, 'Raw Data'!B:B, "Yes")/COUNTIF('Raw Data'!P:P, F8) -> 0.06870229
A9: No | B9: =ROUND(AVERAGEIF('Raw Data'!B:B, A9, 'Raw Data'!S:S), 2) -> 6832.74 | F9: Manager | G9: =COUNTIF('Raw Data'!P:P, F9) -> 102 | H9: =COUNTIFS('Raw Data'!P:P, F9, 'Raw Data'!B:B, "Yes") -> 5 | I9: =COUNTIFS('Raw Data'!P:P, F9, 'Raw Data'!B:B, "Yes")/COUNTIF('Raw Data'!P:P, F9) -> 0.049019608
F10: Research Director | G10: =COUNTIF('Raw Data'!P:P, F10) -> 80 | H10: =COUNTIFS('Raw Data'!P:P, F10, 'Raw Data'!B:B, "Yes") -> 2 | I10: =COUNTIFS('Raw Data'!P:P, F10, 'Raw Data'!B:B, "Yes")/COUNTIF('Raw Data'!P:P, F10) -> 0.025
A12: Overtime | B12: Total Employees | C12: Employees Left | D12: Attrition Rate
A13: Yes | B13: =COUNTIF('Raw Data'!W:W, A13) -> 416 | C13: =COUNTIFS('Raw Data'!W:W, A13, 'Raw Data'!B:B, "Yes") -> 127 | D13: =C13/B13 -> 0.30528846
A14: No | B14: =COUNTIF('Raw Data'!W:W, A14) -> 1054 | C14: =COUNTIFS('Raw Data'!W:W,A14, 'Raw Data'!B:B, "Yes") -> 110 | D14: =C14/B14 -> 0.10436433
A17: Work Life Balance | B17: Total Employees | C17: Employees Left | D17: Attrition Rate | E17: 1
A18: 1 - Bad | B18: =COUNTIF('Raw Data'!AE:AE, E17) -> 80 | C18: =COUNTIFS('Raw Data'!AE:AE, E17, 'Raw Data'!B:B, "Yes") -> 25 | D18: =C18/B18 -> 0.3125 | E18: 2
A19: 2 - Fair | B19: =COUNTIF('Raw Data'!AE:AE, E18) -> 344 | C19: =COUNTIFS('Raw Data'!AE:AE, E18, 'Raw Data'!B:B, "Yes") -> 58 | D19: =C19/B19 -> 0.16860465 | E19: 3
A20: 3 - Good | B20: =COUNTIF('Raw Data'!AE:AE, E19) -> 893 | C20: =COUNTIFS('Raw Data'!AE:AE, E19, 'Raw Data'!B:B, "Yes") -> 127 | D20: =C20/B20 -> 0.14221725 | E20: 4
A21: 4 - Excellent | B21: =COUNTIF('Raw Data'!AE:AE, E20) -> 153 | C21: =COUNTIFS('Raw Data'!AE:AE, E20, 'Raw Data'!B:B, "Yes") -> 27 | D21: =C21/B21 -> 0.17647059

Sheet Dashboard
B2: IBM HR Attrition Analysis
B4: Total Employees | C4: Employees Left | D4: Attrition Rate
B5: =COUNT('Raw Data'!A:A) -> 1470 | C5: =COUNTIF('Raw Data'!B:B, "Yes") -> 237 | D5: =C5/B5 -> 0.16122449

Sheet Insights
A1: IBM HR Attrition Analysis — Key Findings
A2: =========================================
A4: HEADLINE
A5: Overall attrition rate is 16%, meaning 237 of 1,470 employees
A6: left the company.
A8: FINDING 1 — COMPENSATION IS THE BIGGEST DRIVER
A9: Employees who left earned an average of $4,787/month compared
A10: to $6,833 for those who stayed — a 30% income gap suggesting
A11: compensation is a primary attrition driver.
A13: FINDING 2 — OVERTIME TRIPLES ATTRITION RISK
A14: Employees working overtime have a 31% attrition rate versus
A15: 10% for those who don't — making overtime the single strongest
... A34: given the 40% attrition rate in that role.
