Workbook

Sheet vgsales
A1: Rank | B1: Name | C1: Platform | D1: Year | E1: Genre | F1: Publisher | G1: NA_Sales | H1: EU_Sales | I1: JP_Sales | J1: Other_Sales | K1: Global_Sales | L1: Sales Category | M1: Platform Code | N1: Game Summary
A2: 1 | B2: Wii Sports | C2: Wii | D2: 2006 | E2: Sports | F2: Nintendo | G2: 41.49 | H2: 29.02 | I2: 3.77 | J2: 8.46 | K2: 82.74 | L2: =IF(K2 > 10, "Blockbuster", IF(K2 > 1, "Standard", "Niche")) -> Blockbuster | M2: =LEFT(C2, 3) -> Wii | N2: =CONCATENATE(B2, " ", "(", C2, ")") -> Wii Sports (Wii)
A3: 2 | B3: Super Mario Bros. | C3: NES | D3: 1985 | E3: Platform | F3: Nintendo | G3: 29.08 | H3: 3.58 | I3: 6.81 | J3: 0.77 | K3: 40.24 | L3: =IF(K3 > 10, "Blockbuster", IF(K3 > 1, "Standard", "Niche")) -> Blockbuster | M3: =LEFT(C3, 3) -> NES | N3: =CONCATENATE(B3, " ", "(", C3, ")") -> Super Mario Bros. (NES)
A4: 3 | B4: Mario Kart Wii | C4: Wii | D4: 2008 | E4: Racing | F4: Nintendo | G4: 15.85 | H4: 12.88 | I4: 3.79 | J4: 3.31 | K4: 35.82 | L4: =IF(K4 > 10, "Blockbuster", IF(K4 > 1, "Standard", "Niche")) -> Blockbuster | M4: =LEFT(C4, 3) -> Wii | N4: =CONCATENATE(B4, " ", "(", C4, ")") -> Mario Kart Wii (Wii)
A5: 4 | B5: Wii Sports Resort | C5: Wii | D5: 2009 | E5: Sports | F5: Nintendo | G5: 15.75 | H5: 11.01 | I5: 3.28 | J5: 2.96 | K5: 33 | L5: =IF(K5 > 10, "Blockbuster", IF(K5 > 1, "Standard", "Niche")) -> Blockbuster | M5: =LEFT(C5, 3) -> Wii | N5: =CONCATENATE(B5, " ", "(", C5, ")") -> Wii Sports Resort (Wii)
A6: 5 | B6: Pokemon Red/Pokemon Blue | C6: GB | D6: 1996 | E6: Role-Playing | F6: Nintendo | G6: 11.27 | H6: 8.89 | I6: 10.22 | J6: 1 | K6: 31.37 | L6: =IF(K6 > 10, "Blockbuster", IF(K6 > 1, "Standard", "Niche")) -> Blockbuster | M6: =LEFT(C6, 3) -> GB | N6: =CONCATENATE(B6, " ", "(", C6, ")") -> Pokemon Red/Pokemon Blue (GB)
A7: 6 | B7: Tetris | C7: GB | D7: 1989 | E7: Puzzle | F7: Nintendo | G7: 23.2 | H7: 2.26 | I7: 4.22 | J7: 0.58 | K7: 30.26 | L7: =IF(K7 > 10, "Blockbuster", IF(K7 > 1, "Standard", "Niche")) -> Blockbuster | M7: =LEFT(C7, 3) -> GB | N7: =CONCATENATE(B7, " ", "(", C7, ")") -> Tetris (GB)
A8: 7 | B8: New Super Mario Bros. | C8: DS | D8: 2006 | E8: Platform | F8: Nintendo | G8: 11.38 | H8: 9.23 | I8: 6.5 | J8: 2.9 | K8: 30.01 | L8: =IF(K8 > 10, "Blockbuster", IF(K8 > 1, "Standard", "Niche")) -> Blockbuster | M8: =LEFT(C8, 3) -> DS | N8: =CONCATENATE(B8, " ", "(", C8, ")") -> New Super Mario Bros. (DS)
A9: 8 | B9: Wii Play | C9: Wii | D9: 2006 | E9: Misc | F9: Nintendo | G9: 14.03 | H9: 9.2 | I9: 2.93 | J9: 2.85 | K9: 29.02 | L9: =IF(K9 > 10, "Blockbuster", IF(K9 > 1, "Standard", "Niche")) -> Blockbuster | M9: =LEFT(C9, 3) -> Wii | N9: =CONCATENATE(B9, " ", "(", C9, ")") -> Wii Play (Wii)
A10: 9 | B10: New Super Mario Bros. Wii | C10: Wii | D10: 2009 | E10: Platform | F10: Nintendo | G10: 14.59 | H10: 7.06 | I10: 4.7 | J10: 2.26 | K10: 28.62 | L10: =IF(K10 > 10, "Blockbuster", IF(K10 > 1, "Standard", "Niche")) -> Blockbuster | M10: =LEFT(C10, 3) -> Wii | N10: =CONCATENATE(B10, " ", "(", C10, ")") -> New Super Mario Bros. Wii (Wii)
A11: 10 | B11: Duck Hunt | C11: NES | D11: 1984 | E11: Shooter | F11: Nintendo | G11: 26.93 | H11: 0.63 | I11: 0.28 | J11: 0.47 | K11: 28.31 | L11: =IF(K11 > 10, "Blockbuster", IF(K11 > 1, "Standard", "Niche")) -> Blockbuster | M11: =LEFT(C11, 3) -> NES | N11: =CONCATENATE(B11, " ", "(", C11, ")") -> Duck Hunt (NES)
A12: 11 | B12: Nintendogs | C12: DS | D12: 2005 | E12: Simulation | F12: Nintendo | G12: 9.07 | H12: 11 | I12: 1.93 | J12: 2.75 | K12: 24.76 | L12: =IF(K12 > 10, "Blockbuster", IF(K12 > 1, "Standard", "Niche")) -> Blockbuster | M12: =LEFT(C12, 3) -> DS | N12: =CONCATENATE(B12, " ", "(", C12, ")") -> Nintendogs (DS)
A13: 12 | B13: Mario Kart DS | C13: DS | D13: 2005 | E13: Racing | F13: Nintendo | G13: 9.81 | H13: 7.57 | I13: 4.13 | J13: 1.92 | K13: 23.42 | L13: =IF(K13 > 10, "Blockbuster", IF(K13 > 1, "Standard", "Niche")) -> Blockbuster | M13: =LEFT(C13, 3) -> DS | N13: =CONCATENATE(B13, " ", "(", C13, ")") -> Mario Kart DS (DS)
... A90: 89 | B90: PokÃ©mon Platinum Version | C90: DS | D90: 2008 | E90: Role-Playing | F90: Nintendo | G90: 2.82 | H90: 1.78 | I90: 2.69 | J90: 0.55 | K90: 7.84 | L90: =IF(K90 > 10, "Blockbuster", IF(K90 > 1, "Standard", "Niche")) -> Standard | M90: =LEFT(C90, 3) -> DS | N90: =CONCATENATE(B90, " ", "(", C90, ")") -> PokÃ©mon Platinum Version (DS)
A91: 90 | B91: Pac-Man | C91: 2600 | D91: 1982 | E91: Puzzle | F91: Atari | G91: 7.28 | H91: 0.45 | I91: 0 | J91: 0.08 | K91: 7.81 | L91: =IF(K91 > 10, "Blockbuster", IF(K91 > 1, "Standard", "Niche")) -> Standard | M91: =LEFT(C91, 3) -> 260 | N91: =CONCATENATE(B91, " ", "(", C91, ")") -> Pac-Man (2600)
A92: 91 | B92: Grand Theft Auto: Liberty City Stories | C92: PSP | D92: 2005 | E92: Action | F92: Take-Two Interactive | G92: 2.9 | H92: 2.83 | I92: 0.24 | J92: 1.75 | K92: 7.72 | L92: =IF(K92 > 10, "Blockbuster", IF(K92 > 1, "Standard", "Niche")) -> Standard | M92: =LEFT(C92, 3) -> PSP | N92: =CONCATENATE(B92, " ", "(", C92, ")") -> Grand Theft Auto: Liberty City Stories (PSP)
A93: 92 | B93: Super Mario Galaxy 2 | C93: Wii | D93: 2010 | E93: Platform | F93: Nintendo | G93: 3.66 | H93: 2.42 | I93: 0.98 | J93: 0.64 | K93: 7.69 | L93: =IF(K93 > 10, "Blockbuster", IF(K93 > 1, "Standard", "Niche")) -> Standard | M93: =LEFT(C93, 3) -> Wii | N93: =CONCATENATE(B93, " ", "(", C93, ")") -> Super Mario Galaxy 2 (Wii)
A94: 93 | B94: Star Wars Battlefront (2015) | C94: PS4 | D94: 2015 | E94: Shooter | F94: Electronic Arts | G94: 2.93 | H94: 3.29 | I94: 0.22 | J94: 1.23 | K94: 7.67 | L94: =IF(K94 > 10, "Blockbuster", IF(K94 > 1, "Standard", "Niche")) -> Standard | M94: =LEFT(C94, 3) -> PS4 | N94: =CONCATENATE(B94, " ", "(", C94, ")") -> Star Wars Battlefront (2015) (PS4)
A95: 94 | B95: Call of Duty: Advanced Warfare | C95: PS4 | D95: 2014 | E95: Shooter | F95: Activision | G95: 2.8 | H95: 3.3 | I95: 0.14 | J95: 1.37 | K95: 7.6 | L95: =IF(K95 > 10, "Blockbuster", IF(K95 > 1, "Standard", "Niche")) -> Standard | M95: =LEFT(C95, 3) -> PS4 | N95: =CONCATENATE(B95, " ", "(", C95, ")") -> Call of Duty: Advanced Warfare (PS4)
A96: 95 | B96: The Legend of Zelda: Ocarina of Time | C96: N64 | D96: 1998 | E96: Action | F96: Nintendo | G96: 4.1 | H96: 1.89 | I96: 1.45 | J96: 0.16 | K96: 7.6 | L96: =IF(K96 > 10, "Blockbuster", IF(K96 > 1, "Standard", "Niche")) -> Standard | M96: =LEFT(C96, 3) -> N64 | N96: =CONCATENATE(B96, " ", "(", C96, ")") -> The Legend of Zelda: Ocarina of Time (N64)
A97: 96 | B97: Crash Bandicoot 2: Cortex Strikes Back | C97: PS | D97: 1997 | E97: Platform | F97: Sony Computer Entertainment | G97: 3.78 | H97: 2.17 | I97: 1.31 | J97: 0.31 | K97: 7.58 | L97: =IF(K97 > 10, "Blockbuster", IF(K97 > 1, "Standard", "Niche")) -> Standard | M97: =LEFT(C97, 3) -> PS | N97: =CONCATENATE(B97, " ", "(", C97, ")") -> Crash Bandicoot 2: Cortex Strikes Back (PS)
A98: 97 | B98: Super Mario Bros. 2 | C98: NES | D98: 1988 | E98: Platform | F98: Nintendo | G98: 5.39 | H98: 1.18 | I98: 0.7 | J98: 0.19 | K98: 7.46 | L98: =IF(K98 > 10, "Blockbuster", IF(K98 > 1, "Standard", "Niche")) -> Standard | M98: =LEFT(C98, 3) -> NES | N98: =CONCATENATE(B98, " ", "(", C98, ")") -> Super Mario Bros. 2 (NES)
A99: 98 | B99: Super Smash Bros. for Wii U and 3DS | C99: 3DS | D99: 2014 | E99: Fighting | F99: Nintendo | G99: 3.24 | H99: 1.35 | I99: 2.42 | J99: 0.43 | K99: 7.45 | L99: =IF(K99 > 10, "Blockbuster", IF(K99 > 1, "Standard", "Niche")) -> Standard | M99: =LEFT(C99, 3) -> 3DS | N99: =CONCATENATE(B99, " ", "(", C99, ")") -> Super Smash Bros. for Wii U and 3DS (3DS)
A100: 99 | B100: Call of Duty: World at War | C100: X360 | D100: 2008 | E100: Shooter | F100: Activision | G100: 4.79 | H100: 1.9 | I100: 0 | J100: 0.69 | K100: 7.37 | L100: =IF(K100 > 10, "Blockbuster", IF(K100 > 1, "Standard", "Niche")) -> Standard | M100: =LEFT(C100, 3) -> X36 | N100: =CONCATENATE(B100, " ", "(", C100, ")") -> Call of Duty: World at War (X360)
A101: 100 | B101: Battlefield 3 | C101: X360 | D101: 2011 | E101: Shooter | F101: Electronic Arts | G101: 4.46 | H101: 2.13 | I101: 0.06 | J101: 0.69 | K101: 7.34 | L101: =IF(K101 > 10, "Blockbuster", IF(K101 > 1, "Standard", "Niche")) -> Standard | M101: =LEFT(C101, 3) -> X36 | N101: =CONCATENATE(B101, " ", "(", C101, ")") -> Battlefield 3 (X360)
A102: 101 | B102: The Legend of Zelda: Twilight Princess | C102: Wii | D102: 2006 | E102: Action | F102: Nintendo | G102: 3.83 | H102: 2.19 | I102: 0.6 | J102: 0.7 | K102: 7.31 | L102: =IF(K102 > 10, "Blockbuster", IF(K102 > 1, "Standard", "Niche")) -> Standard | M102: =LEFT(C102, 3) -> Wii | N102: =CONCATENATE(B102, " ", "(", C102, ")") -> The Legend of Zelda: Twilight Princess (Wii)
A103: 102 | B103: Call of Duty: Black Ops 3 | C103: XOne | D103: 2015 | E103: Shooter | F103: Activision | G103: 4.52 | H103: 2.09 | I103: 0.01 | J103: 0.67 | K103: 7.3 | L103: =IF(K103 > 10, "Blockbuster", IF(K103 > 1, "Standard", "Niche")) -> Standard | M103: =LEFT(C103, 3) -> XOn | N103: =CONCATENATE(B103, " ", "(", C103, ")") -> Call of Duty: Black Ops 3 (XOne)
... A180: 179 | B180: Tomb Raider II | C180: PS | D180: 1997 | E180: Action | F180: Eidos Interactive | G180: 2.3 | H180: 2.46 | I180: 0.2 | J180: 0.28 | K180: 5.24 | L180: =IF(K180 > 10, "Blockbuster", IF(K180 > 1, "Standard", "Niche")) -> Standard | M180: =LEFT(C180, 3) -> PS | N180: =CONCATENATE(B180, " ", "(", C180, ")") -> Tomb Raider II (PS)
A181: 180 | B181: Madden NFL 2004 | C181: PS2 | D181: N/A | E181: Sports | F181: Electronic Arts | G181: 4.26 | H181: 0.26 | I181: 0.01 | J181: 0.71 | K181: 5.23 | L181: =IF(K181 > 10, "Blockbuster", IF(K181 > 1, "Standard", "Niche")) -> Standard | M181: =LEFT(C181, 3) -> PS2 | N181: =CONCATENATE(B181, " ", "(", C181, ")") -> Madden NFL 2004 (PS2)
A182: 181 | B182: Dragon Quest VIII: Journey of the Cursed King | C182: PS2 | D182: 2004 | E182: Role-Playing | F182: Square Enix | G182: 0.65 | H182: 0.75 | I182: 3.61 | J182: 0.2 | K182: 5.21 | L182: =IF(K182 > 10, "Blockbuster", IF(K182 > 1, "Standard", "Niche")) -> Standard | M182: =LEFT(C182, 3) -> PS2 | N182: =CONCATENATE(B182, " ", "(", C182, ")") -> Dragon Quest VIII: Journey of the Cursed King (PS2)
A183: 182 | B183: Diablo III | C183: PC | D183: 2012 | E183: Role-Playing | F183: Activision | G183: 2.43 | H183: 2.15 | I183: 0 | J183: 0.62 | K183: 5.2 | L183: =IF(K183 > 10, "Blockbuster", IF(K183 > 1, "Standard", "Niche")) -> Standard | M183: =LEFT(C183, 3) -> PC | N183: =CONCATENATE(B183, " ", "(", C183, ")") -> Diablo III (PC)
A184: 183 | B184: Super Mario Bros. 3 | C184: GBA | D184: 2003 | E184: Platform | F184: Nintendo | G184: 2.93 | H184: 1.25 | I184: 0.83 | J184: 0.2 | K184: 5.2 | L184: =IF(K184 > 10, "Blockbuster", IF(K184 > 1, "Standard", "Niche")) -> Standard | M184: =LEFT(C184, 3) -> GBA | N184: =CONCATENATE(B184, " ", "(", C184, ")") -> Super Mario Bros. 3 (GBA)
A185: 184 | B185: New Super Mario Bros. U | C185: WiiU | D185: 2012 | E185: Platform | F185: Nintendo | G185: 2.32 | H185: 1.3 | I185: 1.27 | J185: 0.31 | K185: 5.19 | L185: =IF(K185 > 10, "Blockbuster", IF(K185 > 1, "Standard", "Niche")) -> Standard | M185: =LEFT(C185, 3) -> Wii | N185: =CONCATENATE(B185, " ", "(", C185, ")") -> New Super Mario Bros. U (WiiU)
A186: 185 | B186: Super Mario Land 3: Wario Land | C186: GB | D186: 1994 | E186: Platform | F186: Nintendo | G186: 2.49 | H186: 0.98 | I186: 1.57 | J186: 0.15 | K186: 5.19 | L186: =IF(K186 > 10, "Blockbuster", IF(K186 > 1, "Standard", "Niche")) -> Standard | M186: =LEFT(C186, 3) -> GB | N186: =CONCATENATE(B186, " ", "(", C186, ")") -> Super Mario Land 3: Wario Land (GB)
A187: 186 | B187: FIFA Soccer 13 | C187: X360 | D187: 2012 | E187: Action | F187: Electronic Arts | G187: 1.08 | H187: 3.48 | I187: 0.03 | J187: 0.58 | K187: 5.18 | L187: =IF(K187 > 10, "Blockbuster", IF(K187 > 1, "Standard", "Niche")) -> Standard | M187: =LEFT(C187, 3) -> X36 | N187: =CONCATENATE(B187, " ", "(", C187, ")") -> FIFA Soccer 13 (X360)
A188: 187 | B188: The Legend of Zelda: Phantom Hourglass | C188: DS | D188: 2007 | E188: Action | F188: Nintendo | G188: 1.9 | H188: 1.83 | I188: 0.95 | J188: 0.49 | K188: 5.17 | L188: =IF(K188 > 10, "Blockbuster", IF(K188 > 1, "Standard", "Niche")) -> Standard | M188: =LEFT(C188, 3) -> DS | N188: =CONCATENATE(B188, " ", "(", C188, ")") -> The Legend of Zelda: Phantom Hourglass (DS)
A189: 188 | B189: Donkey Kong Country 2: Diddy's Kong Quest | C189: SNES | D189: 1995 | E189: Platform | F189: Nintendo | G189: 2.1 | H189: 0.74 | I189: 2.2 | J189: 0.11 | K189: 5.15 | L189: =IF(K189 > 10, "Blockbuster", IF(K189 > 1, "Standard", "Niche")) -> Standard | M189: =LEFT(C189, 3) -> SNE | N189: =CONCATENATE(B189, " ", "(", C189, ")") -> Donkey Kong Country 2: Diddy's Kong Quest (SNES)
A190: 189 | B190: Tomodachi Life | C190: 3DS | D190: 2013 | E190: Simulation | F190: Nintendo | G190: 0.96 | H190: 2.02 | I190: 1.89 | J190: 0.28 | K190: 5.15 | L190: =IF(K190 > 10, "Blockbuster", IF(K190 > 1, "Standard", "Niche")) -> Standard | M190: =LEFT(C190, 3) -> 3DS | N190: =CONCATENATE(B190, " ", "(", C190, ")") -> Tomodachi Life (3DS)
A191: 190 | B191: Mario & Sonic at the Olympic Games | C191: DS | D191: 2008 | E191: Sports | F191: Sega | G191: 1.64 | H191: 2.48 | I191: 0.44 | J191: 0.58 | K191: 5.14 | L191: =IF(K191 > 10, "Blockbuster", IF(K191 > 1, "Standard", "Niche")) -> Standard | M191: =LEFT(C191, 3) -> DS | N191: =CONCATENATE(B191, " ", "(", C191, ")") -> Mario & Sonic at the Olympic Games (DS)
A192: 191 | B192: Medal of Honor: Rising Sun | C192: PS2 | D192: 2003 | E192: Shooter | F192: Electronic Arts | G192: 1.98 | H192: 2.23 | I192: 0.13 | J192: 0.8 | K192: 5.13 | L192: =IF(K192 > 10, "Blockbuster", IF(K192 > 1, "Standard", "Niche")) -> Standard | M192: =LEFT(C192, 3) -> PS2 | N192: =CONCATENATE(B192, " ", "(", C192, ")") -> Medal of Honor: Rising Sun (PS2)
A193: 192 | B193: Kirby's Dream Land | C193: GB | D193: 1992 | E193: Platform | F193: Nintendo | G193: 2.71 | H193: 0.61 | I193: 1.7 | J193: 0.11 | K193: 5.13 | L193: =IF(K193 > 10, "Blockbuster", IF(K193 > 1, "Standard", "Niche")) -> Standard | M193: =LEFT(C193, 3) -> GB | N193: =CONCATENATE(B193, " ", "(", C193, ")") -> Kirby's Dream Land (GB)
... A240: 239 | B240: Madden NFL 2005 | C240: PS2 | D240: 2004 | E240: Sports | F240: Electronic Arts | G240: 4.18 | H240: 0.26 | I240: 0.01 | J240: 0.08 | K240: 4.53 | L240: =IF(K240 > 10, "Blockbuster", IF(K240 > 1, "Standard", "Niche")) -> Standard | M240: =LEFT(C240, 3) -> PS2 | N240: =CONCATENATE(B240, " ", "(", C240, ")") -> Madden NFL 2005 (PS2)
A241: 240 | B241: Pitfall! | C241: 2600 | D241: 1981 | E241: Platform | F241: Activision | G241: 4.21 | H241: 0.24 | I241: 0 | J241: 0.05 | K241: 4.5 | L241: =IF(K241 > 10, "Blockbuster", IF(K241 > 1, "Standard", "Niche")) -> Standard | M241: =LEFT(C241, 3) -> 260 | N241: =CONCATENATE(B241, " ", "(", C241, ")") -> Pitfall! (2600)
A242: 241 | B242: Madden NFL 07 | C242: PS2 | D242: 2006 | E242: Sports | F242: Electronic Arts | G242: 3.63 | H242: 0.24 | I242: 0.01 | J242: 0.61 | K242: 4.49 | L242: =IF(K242 > 10, "Blockbuster", IF(K242 > 1, "Standard", "Niche")) -> Standard | M242: =LEFT(C242, 3) -> PS2 | N242: =CONCATENATE(B242, " ", "(", C242, ")") -> Madden NFL 07 (PS2)
A243: 242 | B243: Spider-Man: The Movie | C243: PS2 | D243: 2002 | E243: Action | F243: Activision | G243: 2.71 | H243: 1.51 | I243: 0.03 | J243: 0.23 | K243: 4.48 | L243: =IF(K243 > 10, "Blockbuster", IF(K243 > 1, "Standard", "Niche")) -> Standard | M243: =LEFT(C243, 3) -> PS2 | N243: =CONCATENATE(B243, " ", "(", C243, ")") -> Spider-Man: The Movie (PS2)
A244: 243 | B244: Dragon Quest VII: Warriors of Eden | C244: PS | D244: 2000 | E244: Role-Playing | F244: Enix Corporation | G244: 0.2 | H244: 0.14 | I244: 4.1 | J244: 0.02 | K244: 4.47 | L244: =IF(K244 > 10, "Blockbuster", IF(K244 > 1, "Standard", "Niche")) -> Standard | M244: =LEFT(C244, 3) -> PS | N244: =CONCATENATE(B244, " ", "(", C244, ")") -> Dragon Quest VII: Warriors of Eden (PS)
A245: 244 | B245: Uncharted: The Nathan Drake Collection | C245: PS4 | D245: 2015 | E245: Action | F245: Sony Computer Entertainment | G245: 1.96 | H245: 1.69 | I245: 0.08 | J245: 0.74 | K245: 4.47 | L245: =IF(K245 > 10, "Blockbuster", IF(K245 > 1, "Standard", "Niche")) -> Standard | M245: =LEFT(C245, 3) -> PS4 | N245: =CONCATENATE(B245, " ", "(", C245, ")") -> Uncharted: The Nathan Drake Collection (PS4)
A246: 245 | B246: Call of Duty: Advanced Warfare | C246: PS3 | D246: 2014 | E246: Shooter | F246: Activision | G246: 1.54 | H246: 1.94 | I246: 0.19 | J246: 0.77 | K246: 4.45 | L246: =IF(K246 > 10, "Blockbuster", IF(K246 > 1, "Standard", "Niche")) -> Standard | M246: =LEFT(C246, 3) -> PS3 | N246: =CONCATENATE(B246, " ", "(", C246, ")") -> Call of Duty: Advanced Warfare (PS3)
A247: 246 | B247: God of War | C247: PS2 | D247: 2005 | E247: Action | F247: Sony Computer Entertainment | G247: 2.71 | H247: 1.29 | I247: 0.02 | J247: 0.43 | K247: 4.45 | L247: =IF(K247 > 10, "Blockbuster", IF(K247 > 1, "Standard", "Niche")) -> Standard | M247: =LEFT(C247, 3) -> PS2 | N247: =CONCATENATE(B247, " ", "(", C247, ")") -> God of War (PS2)
A248: 247 | B248: Nintendo Land | C248: WiiU | D248: 2012 | E248: Misc | F248: Nintendo | G248: 2.55 | H248: 1.11 | I248: 0.46 | J248: 0.33 | K248: 4.44 | L248: =IF(K248 > 10, "Blockbuster", IF(K248 > 1, "Standard", "Niche")) -> Standard | M248: =LEFT(C248, 3) -> Wii | N248: =CONCATENATE(B248, " ", "(", C248, ")") -> Nintendo Land (WiiU)
A249: 248 | B249: Michael Jackson: The Experience | C249: Wii | D249: 2010 | E249: Misc | F249: Ubisoft | G249: 2.67 | H249: 1.35 | I249: 0.01 | J249: 0.39 | K249: 4.42 | L249: =IF(K249 > 10, "Blockbuster", IF(K249 > 1, "Standard", "Niche")) -> Standard | M249: =LEFT(C249, 3) -> Wii | N249: =CONCATENATE(B249, " ", "(", C249, ")") -> Michael Jackson: The Experience (Wii)
A250: 249 | B250: Tony Hawk's Pro Skater 3 | C250: PS2 | D250: 2001 | E250: Sports | F250: Activision | G250: 2.66 | H250: 1.29 | I250: 0.01 | J250: 0.46 | K250: 4.41 | L250: =IF(K250 > 10, "Blockbuster", IF(K250 > 1, "Standard", "Niche")) -> Standard | M250: =LEFT(C250, 3) -> PS2 | N250: =CONCATENATE(B250, " ", "(", C250, ")") -> Tony Hawk's Pro Skater 3 (PS2)
A251: 250 | B251: Winning Eleven: Pro Evolution Soccer 2007 | C251: PS2 | D251: 2006 | E251: Sports | F251: Konami Digital Entertainment | G251: 0.1 | H251: 2.39 | I251: 1.05 | J251: 0.86 | K251: 4.39 | L251: =IF(K251 > 10, "Blockbuster", IF(K251 > 1, "Standard", "Niche")) -> Standard | M251: =LEFT(C251, 3) -> PS2 | N251: =CONCATENATE(B251, " ", "(", C251, ")") -> Winning Eleven: Pro Evolution Soccer 2007 (PS2)
A252: 251 | B252: The Elder Scrolls IV: Oblivion | C252: X360 | D252: 2006 | E252: Role-Playing | F252: Take-Two Interactive | G252: 2.82 | H252: 1.05 | I252: 0.13 | J252: 0.4 | K252: 4.39 | L252: =IF(K252 > 10, "Blockbuster", IF(K252 > 1, "Standard", "Niche")) -> Standard | M252: =LEFT(C252, 3) -> X36 | N252: =CONCATENATE(B252, " ", "(", C252, ")") -> The Elder Scrolls IV: Oblivion (X360)
A253: 252 | B253: Zelda II: The Adventure of Link | C253: NES | D253: 1987 | E253: Adventure | F253: Nintendo | G253: 2.19 | H253: 0.5 | I253: 1.61 | J253: 0.08 | K253: 4.38 | L253: =IF(K253 > 10, "Blockbuster", IF(K253 > 1, "Standard", "Niche")) -> Standard | M253: =LEFT(C253, 3) -> NES | N253: =CONCATENATE(B253, " ", "(", C253, ")") -> Zelda II: The Adventure of Link (NES)
... A259: 258 | B259: Call of Duty: Advanced Warfare | C259: X360 | D259: 2014 | E259: Shooter | F259: Activision | G259: 2.75 | H259: 1.18 | I259: 0 | J259: 0.37 | K259: 4.31 | L259: =IF(K259 > 10, "Blockbuster", IF(K259 > 1, "Standard", "Niche")) -> Standard | M259: =LEFT(C259, 3) -> X36 | N259: =CONCATENATE(B259, " ", "(", C259, ")") -> Call of Duty: Advanced Warfare (X360)
A260: 259 | B260: Asteroids | C260: 2600 | D260: 1980 | E260: Shooter | F260: Atari | G260: 4 | H260: 0.26 | I260: 0 | J260: 0.05 | K260: 4.31 | L260: =IF(K260 > 10, "Blockbuster", IF(K260 > 1, "Standard", "Niche")) -> Standard | M260: =LEFT(C260, 3) -> 260 | N260: =CONCATENATE(B260, " ", "(", C260, ")") -> Asteroids (2600)
A261: 260 | B261: Fable II | C261: X360 | D261: 2008 | E261: Role-Playing | F261: Microsoft Game Studios | G261: 2.51 | H261: 1.27 | I261: 0.11 | J261: 0.41 | K261: 4.31 | L261: =IF(K261 > 10, "Blockbuster", IF(K261 > 1, "Standard", "Niche")) -> Standard | M261: =LEFT(C261, 3) -> X36 | N261: =CONCATENATE(B261, " ", "(", C261, ")") -> Fable II (X360)
A262: 261 | B262: Halo 5: Guardians | C262: XOne | D262: 2015 | E262: Shooter | F262: Microsoft Game Studios | G262: 2.64 | H262: 1.2 | I262: 0.03 | J262: 0.39 | K262: 4.26 | L262: =IF(K262 > 10, "Blockbuster", IF(K262 > 1, "Standard", "Niche")) -> Standard | M262: =LEFT(C262, 3) -> XOn | N262: =CONCATENATE(B262, " ", "(", C262, ")") -> Halo 5: Guardians (XOne)
A263: 262 | B263: Super Mario 3D World | C263: WiiU | D263: 2013 | E263: Platform | F263: Nintendo | G263: 2.11 | H263: 1.11 | I263: 0.72 | J263: 0.3 | K263: 4.25 | L263: =IF(K263 > 10, "Blockbuster", IF(K263 > 1, "Standard", "Niche")) -> Standard | M263: =LEFT(C263, 3) -> Wii | N263: =CONCATENATE(B263, " ", "(", C263, ")") -> Super Mario 3D World (WiiU)
A264: 263 | B264: Batman: Arkham Asylum | C264: PS3 | D264: 2009 | E264: Action | F264: Eidos Interactive | G264: 2.23 | H264: 1.34 | I264: 0.07 | J264: 0.61 | K264: 4.25 | L264: =IF(K264 > 10, "Blockbuster", IF(K264 > 1, "Standard", "Niche")) -> Standard | M264: =LEFT(C264, 3) -> PS3 | N264: =CONCATENATE(B264, " ", "(", C264, ")") -> Batman: Arkham Asylum (PS3)
A265: 264 | B265: Assassin's Creed: Revelations | C265: PS3 | D265: 2011 | E265: Action | F265: Ubisoft | G265: 1.41 | H265: 2.02 | I265: 0.1 | J265: 0.72 | K265: 4.24 | L265: =IF(K265 > 10, "Blockbuster", IF(K265 > 1, "Standard", "Niche")) -> Standard | M265: =LEFT(C265, 3) -> PS3 | N265: =CONCATENATE(B265, " ", "(", C265, ")") -> Assassin's Creed: Revelations (PS3)
A266: 265 | B266: Namco Museum | C266: GBA | D266: 2001 | E266: Misc | F266: Namco Bandai Games | G266: 3 | H266: 1.11 | I266: 0.05 | J266: 0.07 | K266: 4.24 | L266: =IF(K266 > 10, "Blockbuster", IF(K266 > 1, "Standard", "Niche")) -> Standard | M266: =LEFT(C266, 3) -> GBA | N266: =CONCATENATE(B266, " ", "(", C266, ")") -> Namco Museum (GBA)
A267: 266 | B267: Metal Gear Solid 3: Snake Eater | C267: PS2 | D267: 2004 | E267: Action | F267: Konami Digital Entertainment | G267: 1.46 | H267: 0 | I267: 0.83 | J267: 1.93 | K267: 4.23 | L267: =IF(K267 > 10, "Blockbuster", IF(K267 > 1, "Standard", "Niche")) -> Standard | M267: =LEFT(C267, 3) -> PS2 | N267: =CONCATENATE(B267, " ", "(", C267, ")") -> Metal Gear Solid 3: Snake Eater (PS2)
A268: 267 | B268: Daxter | C268: PSP | D268: 2006 | E268: Platform | F268: Sony Computer Entertainment | G268: 2.45 | H268: 1.02 | I268: 0 | J268: 0.75 | K268: 4.22 | L268: =IF(K268 > 10, "Blockbuster", IF(K268 > 1, "Standard", "Niche")) -> Standard | M268: =LEFT(C268, 3) -> PSP | N268: =CONCATENATE(B268, " ", "(", C268, ")") -> Daxter (PSP)
A269: 268 | B269: Warcraft II: Tides of Darkness | C269: PC | D269: 1995 | E269: Strategy | F269: Activision | G269: 1.7 | H269: 2.27 | I269: 0 | J269: 0.23 | K269: 4.21 | L269: =IF(K269 > 10, "Blockbuster", IF(K269 > 1, "Standard", "Niche")) -> Standard | M269: =LEFT(C269, 3) -> PC | N269: =CONCATENATE(B269, " ", "(", C269, ")") -> Warcraft II: Tides of Darkness (PC)
A270: 269 | B270: The Legend of Zelda: Ocarina of Time | C270: 3DS | D270: 2011 | E270: Action | F270: Nintendo | G270: 2.03 | H270: 1.27 | I270: 0.62 | J270: 0.3 | K270: 4.21 | L270: =IF(K270 > 10, "Blockbuster", IF(K270 > 1, "Standard", "Niche")) -> Standard | M270: =LEFT(C270, 3) -> 3DS | N270: =CONCATENATE(B270, " ", "(", C270, ")") -> The Legend of Zelda: Ocarina of Time (3DS)
A271: 270 | B271: FIFA Soccer 06 | C271: PS2 | D271: 2005 | E271: Sports | F271: Electronic Arts | G271: 0.78 | H271: 2.55 | I271: 0.04 | J271: 0.84 | K271: 4.21 | L271: =IF(K271 > 10, "Blockbuster", IF(K271 > 1, "Standard", "Niche")) -> Standard | M271: =LEFT(C271, 3) -> PS2 | N271: =CONCATENATE(B271, " ", "(", C271, ")") -> FIFA Soccer 06 (PS2)
A272: 271 | B272: EyeToy Play | C272: PS2 | D272: 2003 | E272: Misc | F272: Sony Computer Entertainment | G272: 0.88 | H272: 2.3 | I272: 0.2 | J272: 0.83 | K272: 4.2 | L272: =IF(K272 > 10, "Blockbuster", IF(K272 > 1, "Standard", "Niche")) -> Standard | M272: =LEFT(C272, 3) -> PS2 | N272: =CONCATENATE(B272, " ", "(", C272, ")") -> EyeToy Play (PS2)
... A378: 377 | B378: Clubhouse Games | C378: DS | D378: 2006 | E378: Misc | F378: Nintendo | G378: 0.59 | H378: 1.83 | I378: 0.73 | J378: 0.35 | K378: 3.5 | L378: =IF(K378 > 10, "Blockbuster", IF(K378 > 1, "Standard", "Niche")) -> Standard | M378: =LEFT(C378, 3) -> DS | N378: =CONCATENATE(B378, " ", "(", C378, ")") -> Clubhouse Games (DS)
A379: 378 | B379: FIFA Soccer 2004 | C379: PS2 | D379: N/A | E379: Sports | F379: Electronic Arts | G379: 0.59 | H379: 2.36 | I379: 0.04 | J379: 0.51 | K379: 3.49 | L379: =IF(K379 > 10, "Blockbuster", IF(K379 > 1, "Standard", "Niche")) -> Standard | M379: =LEFT(C379, 3) -> PS2 | N379: =CONCATENATE(B379, " ", "(", C379, ")") -> FIFA Soccer 2004 (PS2)
A380: 379 | B380: Star Wars Battlefront (2015) | C380: XOne | D380: 2015 | E380: Shooter | F380: Electronic Arts | G380: 1.94 | H380: 1.22 | I380: 0.02 | J380: 0.31 | K380: 3.49 | L380: =IF(K380 > 10, "Blockbuster", IF(K380 > 1, "Standard", "Niche")) -> Standard | M380: =LEFT(C380, 3) -> XOn | N380: =CONCATENATE(B380, " ", "(", C380, ")") -> Star Wars Battlefront (2015) (XOne)
A381: 380 | B381: Battlefield: Bad Company 2 | C381: X360 | D381: 2010 | E381: Shooter | F381: Electronic Arts | G381: 2.09 | H381: 1.02 | I381: 0.04 | J381: 0.32 | K381: 3.48 | L381: =IF(K381 > 10, "Blockbuster", IF(K381 > 1, "Standard", "Niche")) -> Standard | M381: =LEFT(C381, 3) -> X36 | N381: =CONCATENATE(B381, " ", "(", C381, ")") -> Battlefield: Bad Company 2 (X360)
A382: 381 | B382: Guitar Hero: On Tour | C382: DS | D382: 2008 | E382: Misc | F382: Activision | G382: 2.11 | H382: 1.01 | I382: 0.01 | J382: 0.35 | K382: 3.48 | L382: =IF(K382 > 10, "Blockbuster", IF(K382 > 1, "Standard", "Niche")) -> Standard | M382: =LEFT(C382, 3) -> DS | N382: =CONCATENATE(B382, " ", "(", C382, ")") -> Guitar Hero: On Tour (DS)
A383: 382 | B383: Assassin's Creed: Unity | C383: XOne | D383: 2014 | E383: Action | F383: Ubisoft | G383: 2.26 | H383: 0.89 | I383: 0 | J383: 0.3 | K383: 3.46 | L383: =IF(K383 > 10, "Blockbuster", IF(K383 > 1, "Standard", "Niche")) -> Standard | M383: =LEFT(C383, 3) -> XOn | N383: =CONCATENATE(B383, " ", "(", C383, ")") -> Assassin's Creed: Unity (XOne)
A384: 383 | B384: Far Cry 3 | C384: PS3 | D384: 2012 | E384: Shooter | F384: Ubisoft | G384: 0.88 | H384: 1.75 | I384: 0.1 | J384: 0.72 | K384: 3.45 | L384: =IF(K384 > 10, "Blockbuster", IF(K384 > 1, "Standard", "Niche")) -> Standard | M384: =LEFT(C384, 3) -> PS3 | N384: =CONCATENATE(B384, " ", "(", C384, ")") -> Far Cry 3 (PS3)
A385: 384 | B385: Monster Hunter 4 | C385: 3DS | D385: 2013 | E385: Role-Playing | F385: Capcom | G385: 0 | H385: 0 | I385: 3.44 | J385: 0 | K385: 3.44 | L385: =IF(K385 > 10, "Blockbuster", IF(K385 > 1, "Standard", "Niche")) -> Standard | M385: =LEFT(C385, 3) -> 3DS | N385: =CONCATENATE(B385, " ", "(", C385, ")") -> Monster Hunter 4 (3DS)
A386: 385 | B386: Borderlands | C386: X360 | D386: 2009 | E386: Shooter | F386: Take-Two Interactive | G386: 2.39 | H386: 0.73 | I386: 0.03 | J386: 0.29 | K386: 3.44 | L386: =IF(K386 > 10, "Blockbuster", IF(K386 > 1, "Standard", "Niche")) -> Standard | M386: =LEFT(C386, 3) -> X36 | N386: =CONCATENATE(B386, " ", "(", C386, ")") -> Borderlands (X360)
A387: 386 | B387: Tekken 4 | C387: PS2 | D387: 2002 | E387: Fighting | F387: Namco Bandai Games | G387: 1.55 | H387: 1.27 | I387: 0.33 | J387: 0.29 | K387: 3.44 | L387: =IF(K387 > 10, "Blockbuster", IF(K387 > 1, "Standard", "Niche")) -> Standard | M387: =LEFT(C387, 3) -> PS2 | N387: =CONCATENATE(B387, " ", "(", C387, ")") -> Tekken 4 (PS2)
A388: 387 | B388: Battlefield 4 | C388: PS4 | D388: 2013 | E388: Shooter | F388: Electronic Arts | G388: 1.34 | H388: 1.54 | I388: 0.17 | J388: 0.38 | K388: 3.43 | L388: =IF(K388 > 10, "Blockbuster", IF(K388 > 1, "Standard", "Niche")) -> Standard | M388: =LEFT(C388, 3) -> PS4 | N388: =CONCATENATE(B388, " ", "(", C388, ")") -> Battlefield 4 (PS4)
A389: 388 | B389: LittleBigPlanet 2 | C389: PS3 | D389: 2011 | E389: Platform | F389: Sony Computer Entertainment | G389: 1.82 | H389: 1.07 | I389: 0.06 | J389: 0.47 | K389: 3.42 | L389: =IF(K389 > 10, "Blockbuster", IF(K389 > 1, "Standard", "Niche")) -> Standard | M389: =LEFT(C389, 3) -> PS3 | N389: =CONCATENATE(B389, " ", "(", C389, ")") -> LittleBigPlanet 2 (PS3)
A390: 389 | B390: Grand Theft Auto 2 | C390: PS | D390: 1998 | E390: Action | F390: Take-Two Interactive | G390: 1.13 | H390: 2.07 | I390: 0 | J390: 0.22 | K390: 3.42 | L390: =IF(K390 > 10, "Blockbuster", IF(K390 > 1, "Standard", "Niche")) -> Standard | M390: =LEFT(C390, 3) -> PS | N390: =CONCATENATE(B390, " ", "(", C390, ")") -> Grand Theft Auto 2 (PS)
A391: 390 | B391: Final Fantasy III | C391: SNES | D391: 1994 | E391: Role-Playing | F391: SquareSoft | G391: 0.86 | H391: 0 | I391: 2.55 | J391: 0.02 | K391: 3.42 | L391: =IF(K391 > 10, "Blockbuster", IF(K391 > 1, "Standard", "Niche")) -> Standard | M391: =LEFT(C391, 3) -> SNE | N391: =CONCATENATE(B391, " ", "(", C391, ")") -> Final Fantasy III (SNES)
... A432: 431 | B432: Fallout: New Vegas | C432: PS3 | D432: 2010 | E432: Role-Playing | F432: Bethesda Softworks | G432: 1.52 | H432: 1.08 | I432: 0.1 | J432: 0.47 | K432: 3.17 | L432: =IF(K432 > 10, "Blockbuster", IF(K432 > 1, "Standard", "Niche")) -> Standard | M432: =LEFT(C432, 3) -> PS3 | N432: =CONCATENATE(B432, " ", "(", C432, ")") -> Fallout: New Vegas (PS3)
A433: 432 | B433: LEGO Batman: The Videogame | C433: Wii | D433: N/A | E433: Action | F433: Warner Bros. Interactive Entertainment | G433: 1.86 | H433: 1.02 | I433: 0 | J433: 0.29 | K433: 3.17 | L433: =IF(K433 > 10, "Blockbuster", IF(K433 > 1, "Standard", "Niche")) -> Standard | M433: =LEFT(C433, 3) -> Wii | N433: =CONCATENATE(B433, " ", "(", C433, ")") -> LEGO Batman: The Videogame (Wii)
A434: 433 | B434: Rhythm Heaven | C434: DS | D434: 2008 | E434: Misc | F434: Nintendo | G434: 0.58 | H434: 0.51 | I434: 1.93 | J434: 0.14 | K434: 3.17 | L434: =IF(K434 > 10, "Blockbuster", IF(K434 > 1, "Standard", "Niche")) -> Standard | M434: =LEFT(C434, 3) -> DS | N434: =CONCATENATE(B434, " ", "(", C434, ")") -> Rhythm Heaven (DS)
A435: 434 | B435: Ace Combat 04: Shattered Skies | C435: PS2 | D435: 2001 | E435: Simulation | F435: Sony Computer Entertainment Europe | G435: 2.06 | H435: 0.56 | I435: 0.38 | J435: 0.17 | K435: 3.17 | L435: =IF(K435 > 10, "Blockbuster", IF(K435 > 1, "Standard", "Niche")) -> Standard | M435: =LEFT(C435, 3) -> PS2 | N435: =CONCATENATE(B435, " ", "(", C435, ")") -> Ace Combat 04: Shattered Skies (PS2)
A436: 435 | B436: Club Penguin: Elite Penguin Force | C436: DS | D436: 2008 | E436: Adventure | F436: Disney Interactive Studios | G436: 1.88 | H436: 0.98 | I436: 0 | J436: 0.3 | K436: 3.16 | L436: =IF(K436 > 10, "Blockbuster", IF(K436 > 1, "Standard", "Niche")) -> Standard | M436: =LEFT(C436, 3) -> DS | N436: =CONCATENATE(B436, " ", "(", C436, ")") -> Club Penguin: Elite Penguin Force (DS)
A437: 436 | B437: Animal Crossing | C437: GC | D437: 2001 | E437: Simulation | F437: Nintendo | G437: 1.92 | H437: 0.16 | I437: 0.99 | J437: 0.09 | K437: 3.15 | L437: =IF(K437 > 10, "Blockbuster", IF(K437 > 1, "Standard", "Niche")) -> Standard | M437: =LEFT(C437, 3) -> GC | N437: =CONCATENATE(B437, " ", "(", C437, ")") -> Animal Crossing (GC)
A438: 437 | B438: LEGO Batman: The Videogame | C438: DS | D438: 2008 | E438: Action | F438: Warner Bros. Interactive Entertainment | G438: 1.79 | H438: 1.06 | I438: 0 | J438: 0.29 | K438: 3.15 | L438: =IF(K438 > 10, "Blockbuster", IF(K438 > 1, "Standard", "Niche")) -> Standard | M438: =LEFT(C438, 3) -> DS | N438: =CONCATENATE(B438, " ", "(", C438, ")") -> LEGO Batman: The Videogame (DS)
A439: 438 | B439: Sonic Rush | C439: DS | D439: 2005 | E439: Platform | F439: Sega | G439: 1.22 | H439: 1.57 | I439: 0.06 | J439: 0.29 | K439: 3.15 | L439: =IF(K439 > 10, "Blockbuster", IF(K439 > 1, "Standard", "Niche")) -> Standard | M439: =LEFT(C439, 3) -> DS | N439: =CONCATENATE(B439, " ", "(", C439, ")") -> Sonic Rush (DS)
A440: 439 | B440: Resident Evil 6 | C440: PS3 | D440: 2012 | E440: Shooter | F440: Capcom | G440: 0.88 | H440: 0.97 | I440: 0.88 | J440: 0.42 | K440: 3.15 | L440: =IF(K440 > 10, "Blockbuster", IF(K440 > 1, "Standard", "Niche")) -> Standard | M440: =LEFT(C440, 3) -> PS3 | N440: =CONCATENATE(B440, " ", "(", C440, ")") -> Resident Evil 6 (PS3)
A441: 440 | B441: Halo: The Master Chief Collection | C441: XOne | D441: 2014 | E441: Shooter | F441: Microsoft Game Studios | G441: 1.89 | H441: 0.99 | I441: 0.03 | J441: 0.24 | K441: 3.15 | L441: =IF(K441 > 10, "Blockbuster", IF(K441 > 1, "Standard", "Niche")) -> Standard | M441: =LEFT(C441, 3) -> XOn | N441: =CONCATENATE(B441, " ", "(", C441, ")") -> Halo: The Master Chief Collection (XOne)
A442: 441 | B442: FIFA Soccer 08 | C442: PS2 | D442: 2007 | E442: Sports | F442: Electronic Arts | G442: 0.68 | H442: 0 | I442: 0 | J442: 2.46 | K442: 3.14 | L442: =IF(K442 > 10, "Blockbuster", IF(K442 > 1, "Standard", "Niche")) -> Standard | M442: =LEFT(C442, 3) -> PS2 | N442: =CONCATENATE(B442, " ", "(", C442, ")") -> FIFA Soccer 08 (PS2)
A443: 442 | B443: Spider-Man | C443: PS | D443: 2000 | E443: Action | F443: Activision | G443: 1.7 | H443: 1.25 | I443: 0.02 | J443: 0.16 | K443: 3.13 | L443: =IF(K443 > 10, "Blockbuster", IF(K443 > 1, "Standard", "Niche")) -> Standard | M443: =LEFT(C443, 3) -> PS | N443: =CONCATENATE(B443, " ", "(", C443, ")") -> Spider-Man (PS)
A444: 443 | B444: Need for Speed III: Hot Pursuit | C444: PS | D444: 1998 | E444: Racing | F444: Electronic Arts | G444: 2.14 | H444: 0.86 | I444: 0 | J444: 0.13 | K444: 3.12 | L444: =IF(K444 > 10, "Blockbuster", IF(K444 > 1, "Standard", "Niche")) -> Standard | M444: =LEFT(C444, 3) -> PS | N444: =CONCATENATE(B444, " ", "(", C444, ")") -> Need for Speed III: Hot Pursuit (PS)
A445: 444 | B445: Star Wars Episode I Racer | C445: N64 | D445: 1999 | E445: Racing | F445: Nintendo | G445: 2.31 | H445: 0.62 | I445: 0.14 | J445: 0.04 | K445: 3.12 | L445: =IF(K445 > 10, "Blockbuster", IF(K445 > 1, "Standard", "Niche")) -> Standard | M445: =LEFT(C445, 3) -> N64 | N445: =CONCATENATE(B445, " ", "(", C445, ")") -> Star Wars Episode I Racer (N64)
... A471: 470 | B471: Dragon Ball Z: Budokai Tenkaichi 3 | C471: PS2 | D471: 2007 | E471: Fighting | F471: Atari | G471: 1.15 | H471: 0 | I471: 0.76 | J471: 1.09 | K471: 3 | L471: =IF(K471 > 10, "Blockbuster", IF(K471 > 1, "Standard", "Niche")) -> Standard | M471: =LEFT(C471, 3) -> PS2 | N471: =CONCATENATE(B471, " ", "(", C471, ")") -> Dragon Ball Z: Budokai Tenkaichi 3 (PS2)
A472: 471 | B472: wwe Smackdown vs. Raw 2006 | C472: PS2 | D472: N/A | E472: Fighting | F472: N/A | G472: 1.57 | H472: 1.02 | I472: 0 | J472: 0.41 | K472: 3 | L472: =IF(K472 > 10, "Blockbuster", IF(K472 > 1, "Standard", "Niche")) -> Standard | M472: =LEFT(C472, 3) -> PS2 | N472: =CONCATENATE(B472, " ", "(", C472, ")") -> wwe Smackdown vs. Raw 2006 (PS2)
A473: 472 | B473: Middle-Earth: Shadow of Mordor | C473: PS4 | D473: 2014 | E473: Action | F473: Warner Bros. Interactive Entertainment | G473: 1.01 | H473: 1.41 | I473: 0.05 | J473: 0.53 | K473: 2.99 | L473: =IF(K473 > 10, "Blockbuster", IF(K473 > 1, "Standard", "Niche")) -> Standard | M473: =LEFT(C473, 3) -> PS4 | N473: =CONCATENATE(B473, " ", "(", C473, ")") -> Middle-Earth: Shadow of Mordor (PS4)
...

Sheet Lookup Practice
A1: Game | B1: Global Sales (VLOOKUP) | C1: Global Sales (XLOOKUP)
A2: Wii Sports | B2: =IFERROR(VLOOKUP(TRIM(A2),vgsales!B:K,10,FALSE),"Not Found") -> 82.74 | C2: =IFERROR(_xlfn.XLOOKUP(TRIM(A2),vgsales!B:B,vgsales!K:K),"Not Found") -> 82.74
A3: Super Mario Bros. | B3: =IFERROR(VLOOKUP(TRIM(A3),vgsales!B:K,10,FALSE),"Not Found") -> 40.24 | C3: =IFERROR(_xlfn.XLOOKUP(TRIM(A3),vgsales!B:B,vgsales!K:K),"Not Found") -> 40.24
A4: Mario Kart Wii | B4: =IFERROR(VLOOKUP(TRIM(A4),vgsales!B:K,10,FALSE),"Not Found") -> 35.82 | C4: =IFERROR(_xlfn.XLOOKUP(TRIM(A4),vgsales!B:B,vgsales!K:K),"Not Found") -> 35.82
A5: Wii Sports Resort | B5: =IFERROR(VLOOKUP(TRIM(A5),vgsales!B:K,10,FALSE),"Not Found") -> 33 | C5: =IFERROR(_xlfn.XLOOKUP(TRIM(A5),vgsales!B:B,vgsales!K:K),"Not Found") -> 33
A6: Fake Game 2024 | B6: =IFERROR(VLOOKUP(TRIM(A6),vgsales!B:K,10,FALSE),"Not Found") -> Not Found | C6: =IFERROR(_xlfn.XLOOKUP(TRIM(A6),vgsales!B:B,vgsales!K:K),"Not Found") -> Not Found
A7: Wii Sports | B7: =IFERROR(VLOOKUP(TRIM(A7),vgsales!B:K,10,FALSE),"Not Found") -> 82.74 | C7: =IFERROR(_xlfn.XLOOKUP(TRIM(A7),vgsales!B:B,vgsales!K:K),"Not Found") -> 82.74

Sheet Summary
A1: GENRE | B1: GAME COUNT | C1: Global Sales (M) | D1: Average Sales Per Game (M)
A2: Action | B2: =COUNTIF(vgsales!E:E, A2) -> 3316 | C2: =SUMIF(vgsales!E:E, A2, vgsales!K:K) -> 1751.18 | D2: =ROUND(AVERAGEIF(vgsales!E:E, A2, vgsales!K:K),2) -> 0.53
A3: Sports | B3: =COUNTIF(vgsales!E:E, A3) -> 2346 | C3: =SUMIF(vgsales!E:E, A3, vgsales!K:K) -> 1330.93 | D3: =ROUND(AVERAGEIF(vgsales!E:E, A3, vgsales!K:K),2) -> 0.57
A4: Shooter | B4: =COUNTIF(vgsales!E:E, A4) -> 1310 | C4: =SUMIF(vgsales!E:E, A4, vgsales!K:K) -> 1037.37 | D4: =ROUND(AVERAGEIF(vgsales!E:E, A4, vgsales!K:K),2) -> 0.79
A5: Role-Playing | B5: =COUNTIF(vgsales!E:E, A5) -> 1488 | C5: =SUMIF(vgsales!E:E, A5, vgsales!K:K) -> 927.37 | D5: =ROUND(AVERAGEIF(vgsales!E:E, A5, vgsales!K:K),2) -> 0.62
A6: Racing | B6: =COUNTIF(vgsales!E:E, A6) -> 1249 | C6: =SUMIF(vgsales!E:E, A6, vgsales!K:K) -> 732.04 | D6: =ROUND(AVERAGEIF(vgsales!E:E, A6, vgsales!K:K),2) -> 0.59

Sheet Pivot Analysis
A3: Row Labels | B3: Avg Sales Per Game | C3: Sum of Global_Sales
A4: Action | B4: 0.52810012 | C4: 1751.18
A5: Sports | B5: 0.56731884 | C5: 1330.93
A6: Shooter | B6: 0.7918855 | C6: 1037.37
A7: Role-Playing | B7: 0.62323253 | C7: 927.37
A8: Platform | B8: 0.93834086 | C8: 831.37
A9: Misc | B9: 0.46576193 | C9: 809.96
A10: Racing | B10: 0.58610088 | C10: 732.04
A11: Fighting | B11: 0.529375 | C11: 448.91
A12: Simulation | B12: 0.45236448 | C12: 392.2
A13: Puzzle | B13: 0.42087629 | C13: 244.95
A14: Adventure | B14: 0.18587869 | C14: 239.04
A15: Strategy | B15: 0.25715125 | C15: 175.12
A16: Grand Total | B16: 0.53744066 | C16: 8920.44

Sheet Dashboard
G1: VIDEO GAME SALES ANALYSIS
